arcade_brightdata/__init__.py
arcade_brightdata/bright_data_client.py
arcade_brightdata/tools/__init__.py
arcade_brightdata/tools/bright_data_tools.py
arcade_brightdata-0.2.0.dist-info/METADATA
arcade_brightdata-0.2.0.dist-info/WHEEL
arcade_brightdata-0.2.0.dist-info/entry_points.txt
arcade_brightdata-0.2.0.dist-info/licenses/LICENSE
arcade_brightdata-0.2.0.dist-info/RECORD
